__init__.py
main.py
tiniai-1.0.0.dist-info/licenses/LICENSE
tiniai-1.0.0.dist-info/METADATA
tiniai-1.0.0.dist-info/WHEEL
tiniai-1.0.0.dist-info/top_level.txt
tiniai-1.0.0.dist-info/RECORD
