Metadata-Version: 2.4
Name: TiniAI
Version: 1.0.0
Author-email: IrbisX7 <irbisovich123@gmail.com>
Project-URL: Homepage, https://github.com/Irbisovich/tinyai
Project-URL: Issues, https://github.com/Irbisovich/tinyai/issues
Classifier: Programming Language :: Python :: 3
Classifier: License :: OSI Approved :: MIT License
Classifier: Operating System :: OS Independent
Requires-Python: >=3.10.0
License-File: LICENSE
Dynamic: license-file
